compoconf/__init__.py
compoconf/compoconf.py
compoconf/nonstrict_dataclass.py
compoconf/parsing.py
compoconf/util.py
compoconf-0.1.11.dist-info/METADATA
compoconf-0.1.11.dist-info/WHEEL
compoconf-0.1.11.dist-info/licenses/LICENSE
compoconf-0.1.11.dist-info/RECORD
