Metadata-Version: 2.4
Name: compoconf
Version: 0.1.11
Summary: A compositional configuration library for Python
Author-email: Korbinian Pöppel <korbip@korbip.de>
License-Expression: MIT
License-File: LICENSE
Requires-Python: >=3.10
Requires-Dist: dataclasses; python_version < '3.10'
Requires-Dist: typing-extensions>=4.0.0
Provides-Extra: dev
Requires-Dist: black>=23.0.0; extra == 'dev'
Requires-Dist: flake8>=6.0.0; extra == 'dev'
Requires-Dist: isort>=5.12.0; extra == 'dev'
Requires-Dist: mypy>=1.5.0; extra == 'dev'
Requires-Dist: ruff>=0.12.7; extra == 'dev'
Provides-Extra: docs
Requires-Dist: sphinx-autodoc-typehints>=1.25.2; extra == 'docs'
Requires-Dist: sphinx-rtd-theme>=1.3.0; extra == 'docs'
Requires-Dist: sphinx>=7.0.0; extra == 'docs'
Provides-Extra: omegaconf
Requires-Dist: omegaconf>=2.0.0; extra == 'omegaconf'
Provides-Extra: test
Requires-Dist: pytest-cov>=4.0.0; extra == 'test'
Requires-Dist: pytest-sugar>=0.9.7; extra == 'test'
Requires-Dist: pytest>=7.0.0; extra == 'test'
